Metadata-Version: 2.1
Name: tropipy
Version: 0.0.2
Summary: Python SDK for TropiPay
Home-page: https://github.com/ameksike/tropipy
Author: Antonio Membrides Espinosa, Sergio Daniel
Author-email: tonykssa@gmail.com
License: UNKNOWN
Project-URL: Bug Tracker, https://github.com/ameksike/tropipy/issues
Platform: UNKNOWN
Classifier: Programming Language :: Python :: 3
Classifier: License :: OSI Approved :: MIT License
Classifier: Operating System :: OS Independent
Requires-Python: >=3.6
License-File: LICENSE
